redasher.py
redasher/__init__.py
redasher/cli.py
redasher/mapper.py
redasher/redash.py
redasher/repo.py
redasher_ja/__init__.py
redasher_ja/cli.py
redasher_ja/mapper.py
redasher_ja/redash.py
redasher_ja/repo.py
redasher_ja-1.0.0.dist-info/LICENSE
redasher_ja-1.0.0.dist-info/METADATA
redasher_ja-1.0.0.dist-info/WHEEL
redasher_ja-1.0.0.dist-info/entry_points.txt
redasher_ja-1.0.0.dist-info/top_level.txt
redasher_ja-1.0.0.dist-info/RECORD
