Metadata-Version: 2.1
Name: redasher-ja
Version: 1.0.0
Summary: Manage Redash objects as files, enabling version control and development environments. This is a Japanese specialized version of redasher.
Home-page: https://github.com/takeaship/redasher-ja
Author: Takeshi Masukawa
Author-email: spiral.spirit.spider@gmail.com
License: License :: OSI Approved :: GNU Affero General Public License v3 or later (AGPLv3+)
Classifier: Programming Language :: Python :: 3.11
Classifier: Operating System :: POSIX
Classifier: License :: OSI Approved :: GNU Affero General Public License v3 or later (AGPLv3+)
Classifier: Topic :: Scientific/Engineering :: Visualization
Classifier: Topic :: Scientific/Engineering :: Information Analysis
Requires-Python: >=3.7
License-File: LICENSE
Requires-Dist: click
Requires-Dist: requests
Requires-Dist: yamlns
Requires-Dist: consolemsg
Requires-Dist: packaging
Requires-Dist: decorator
Requires-Dist: unidic-lite
Requires-Dist: cutlet
